{
  "aol": {
    "name": "AOL",
    "oauth": false,
    "readonly": false
  },
  "facebook": {
    "name": "Facebook",
    "oauth": true,
    "readonly": false
  },
  "flickr": {
    "name": "Flickr",
    "oauth": true,
    "readonly": false
  },
  "foursquare": {
    "name": "Foursquare",
    "oauth": true,
    "readonly": false
  },
  "github": {
    "name": "GitHub",
    "oauth": true,
    "readonly": false
  },
  "google": {
    "name": "Google",
    "oauth": true,
    "readonly": false
  },
  "imgur": {
    "name": "Imgur",
    "oauth": true,
    "readonly": false
  },
  "instagram": {
    "name": "Instagram",
    "oauth": true,
    "readonly": false
  },
  "linkedin": {
    "name": "LinkedIn",
    "oauth": true,
    "readonly": false
  },
  "reddit": {
    "name": "Reddit",
    "oauth": true,
    "readonly": false
  },
  "steam": {
    "name": "Steam",
    "oauth": false,
    "readonly": false
  },
  "tumblr": {
    "name": "Tumblr",
    "oauth": true,
    "readonly": false
  },
  "twitter": {
    "name": "Twitter",
    "oauth": true,
    "readonly": false
  },
  "yahoo": {
    "name": "Yahoo!",
    "oauth": false,
    "readonly": false
  },
  "windowslive": {
    "name": "Windows Live",
    "oauth": true,
    "readonly": false
  }
}
